astroinject/__init__.py
astroinject/config.py
astroinject/io.py
astroinject/main.py
astroinject/processing.py
astroinject/utils.py
astroinject-1.1.dist-info/licenses/LICENSE
astroinject-1.1.dist-info/METADATA
astroinject-1.1.dist-info/WHEEL
astroinject-1.1.dist-info/entry_points.txt
astroinject-1.1.dist-info/top_level.txt
astroinject-1.1.dist-info/RECORD
