Metadata-Version: 2.4
Name: astroinject
Version: 1.1
Author-email: Gustavo Schwarz <gustavo.b.schwarz@gmail.com>
Requires-Python: >=3.8
License-File: LICENSE
Requires-Dist: numpy
Requires-Dist: pandas
Requires-Dist: psycopg2-binary
Requires-Dist: sqlalchemy
Requires-Dist: pyyaml
Requires-Dist: astropy
Requires-Dist: logpool
Dynamic: license-file
